pytest_playwright_enhanced/__init__.py
pytest_playwright_enhanced/__version__.py
pytest_playwright_enhanced/acquisition.py
pytest_playwright_enhanced/actions.py
pytest_playwright_enhanced/browser_strategy.py
pytest_playwright_enhanced/const.py
pytest_playwright_enhanced/exceptions.py
pytest_playwright_enhanced/hooks.py
pytest_playwright_enhanced/launch_kwargs_strategy.py
pytest_playwright_enhanced/pages/__init__.py
pytest_playwright_enhanced/pages/page.py
pytest_playwright_enhanced/plugin.py
pytest_playwright_enhanced/py.typed
pytest_playwright_enhanced/types.py
pytest_playwright_enhanced/utils.py
pytest_playwright_enhanced-0.2.0.dist-info/LICENSE
pytest_playwright_enhanced-0.2.0.dist-info/METADATA
pytest_playwright_enhanced-0.2.0.dist-info/WHEEL
pytest_playwright_enhanced-0.2.0.dist-info/entry_points.txt
pytest_playwright_enhanced-0.2.0.dist-info/RECORD
