Metadata-Version: 2.1
Name: pytest-playwright-enhanced
Version: 0.2.0
Summary: A pytest plugin for playwright python
Author: Simon K
Author-email: jackofspaces@gmail.com
Requires-Python: >=3.8,<4.0
Classifier: Programming Language :: Python :: 3
Classifier: Programming Language :: Python :: 3.8
Classifier: Programming Language :: Python :: 3.9
Classifier: Programming Language :: Python :: 3.10
Classifier: Programming Language :: Python :: 3.11
Classifier: Programming Language :: Python :: 3.12
Requires-Dist: playwright (>=1.41.2,<2.0.0)
Requires-Dist: pytest (>=8.0.0,<9.0.0)
Requires-Dist: pytest-xdist (>=3.5.0,<4.0.0)
Requires-Dist: python-slugify (>=8.0.4,<9.0.0)
Requires-Dist: types-python-slugify (>=8.0.2.20240310,<9.0.0.0)
